{"nodenames": {"2": "ac prevalence", "9": "cool roofs", "3": "cooling centers", "7": "cooling mitigation", "6": "demographic vulnerability", "0": "extreme heat events", "5": "grid stress test", "8": "heat mitigation", "1": "mortality", "4": "power grid function", "10": "urban forest"}, "graph": [{"id": 2, "edges_out": [7], "edges_in": [], "unit_long": null, "unit_short": null, "values": ["10%", "35%", "60%"], "probs": ["10%:@0.3", "35%:@0.6", "60%:@0.1"]}, {"id": 9, "edges_out": [8], "edges_in": [], "unit_long": null, "unit_short": null, "values": ["10%", "35%", "60%"], "probs": ["10%:@0.3", "35%:@0.5", "60%:@0.2"]}, {"id": 3, "edges_out": [7], "edges_in": [], "unit_long": null, "unit_short": null, "values": ["one per 200", "one per 500", "one per 1000"], "probs": ["one per 200:@0.1", "one per 500:@0.3", "one per 1000:@0.6"]}, {"id": 7, "edges_out": [1], "edges_in": [2, 4, 3], "unit_long": null, "unit_short": null, "values": ["high", "moderate", "low"], "probs": ["high:2;10%;;3;one per 200;;4;good@0.35", "high:2;10%;;3;one per 500;;4;good@0.25", "high:2;10%;;3;one per 1000;;4;good@0.1", "high:2;10%;;3;one per 200;;4;poor@0.1", "high:2;10%;;3;one per 500;;4;poor@0.0", "high:2;10%;;3;one per 1000;;4;poor@0.0", "high:2;35%;;3;one per 200;;4;good@0.5", "high:2;35%;;3;one per 500;;4;good@0.4", "high:2;35%;;3;one per 1000;;4;good@0.3", "high:2;35%;;3;one per 200;;4;poor@0.2", "high:2;35%;;3;one per 500;;4;poor@0.1", "high:2;35%;;3;one per 1000;;4;poor@0.05", "high:2;60%;;3;one per 200;;4;good@0.8", "high:2;60%;;3;one per 500;;4;good@0.6", "high:2;60%;;3;one per 1000;;4;good@0.5", "high:2;60%;;3;one per 200;;4;poor@0.25", "high:2;60%;;3;one per 500;;4;poor@0.15", "high:2;60%;;3;one per 1000;;4;poor@0.1", "moderate:2;10%;;3;one per 200;;4;good@0.05", "moderate:2;10%;;3;one per 500;;4;good@0.05", "moderate:2;10%;;3;one per 1000;;4;good@0.05", "moderate:2;10%;;3;one per 200;;4;poor@0.3", "moderate:2;10%;;3;one per 500;;4;poor@0.3", "moderate:2;10%;;3;one per 1000;;4;poor@0.1", "moderate:2;35%;;3;one per 200;;4;good@0.35", "moderate:2;35%;;3;one per 500;;4;good@0.35", "moderate:2;35%;;3;one per 1000;;4;good@0.3", "moderate:2;35%;;3;one per 200;;4;poor@0.5", "moderate:2;35%;;3;one per 500;;4;poor@0.7", "moderate:2;35%;;3;one per 1000;;4;poor@0.15", "moderate:2;60%;;3;one per 200;;4;good@0.15", "moderate:2;60%;;3;one per 500;;4;good@0.3", "moderate:2;60%;;3;one per 1000;;4;good@0.3", "moderate:2;60%;;3;one per 200;;4;poor@0.35", "moderate:2;60%;;3;one per 500;;4;poor@0.65", "moderate:2;60%;;3;one per 1000;;4;poor@0.1", "low:2;10%;;3;one per 200;;4;good@0.6", "low:2;10%;;3;one per 500;;4;good@0.7", "low:2;10%;;3;one per 1000;;4;good@0.85", "low:2;10%;;3;one per 200;;4;poor@0.6", "low:2;10%;;3;one per 500;;4;poor@0.7", "low:2;10%;;3;one per 1000;;4;poor@0.9", "low:2;35%;;3;one per 200;;4;good@0.15", "low:2;35%;;3;one per 500;;4;good@0.25", "low:2;35%;;3;one per 1000;;4;good@0.4", "low:2;35%;;3;one per 200;;4;poor@0.3", "low:2;35%;;3;one per 500;;4;poor@0.2", "low:2;35%;;3;one per 1000;;4;poor@0.8", "low:2;60%;;3;one per 200;;4;good@0.05", "low:2;60%;;3;one per 500;;4;good@0.1", "low:2;60%;;3;one per 1000;;4;good@0.2", "low:2;60%;;3;one per 200;;4;poor@0.4", "low:2;60%;;3;one per 500;;4;poor@0.2", "low:2;60%;;3;one per 1000;;4;poor@0.8"]}, {"id": 6, "edges_out": [1], "edges_in": [], "unit_long": null, "unit_short": null, "values": ["high", "moderate"], "probs": ["high:@0.3", "moderate:@0.7"]}, {"id": 0, "edges_out": [1], "edges_in": [], "unit_long": null, "unit_short": null, "values": ["many or extended", "few or short"], "probs": ["many or extended:@0.7", "few or short:@0.3"]}, {"id": 5, "edges_out": [], "edges_in": [4], "unit_long": null, "unit_short": null, "values": ["good result", "poor result"], "probs": ["good result:4;good@0.99", "good result:4;poor@0.01", "poor result:4;good@0.01", "poor result:4;poor@0.99"]}, {"id": 8, "edges_out": [1], "edges_in": [9, 10], "unit_long": null, "unit_short": null, "values": ["moderate", "low"], "probs": ["moderate:10;good;;9;10%@0.6", "moderate:10;poor;;9;10%@0.2", "moderate:10;good;;9;35%@0.7", "moderate:10;poor;;9;35%@0.3", "moderate:10;good;;9;60%@0.9", "moderate:10;poor;;9;60%@0.7", "low:10;good;;9;10%@0.4", "low:10;poor;;9;10%@0.8", "low:10;good;;9;35%@0.3", "low:10;poor;;9;35%@0.7", "low:10;good;;9;60%@0.1", "low:10;poor;;9;60%@0.3"]}, {"id": 1, "edges_out": [], "edges_in": [0, 6, 8, 7], "unit_long": null, "unit_short": null, "values": ["high", "moderate", "low"], "probs": ["high:0;many or extended;;6;high;;7;high;;8;moderate@0.3", "high:0;many or extended;;6;high;;7;moderate;;8;moderate@0.5", "high:0;many or extended;;6;high;;7;low;;8;moderate@0.7", "high:0;many or extended;;6;high;;7;high;;8;low@0.65", "high:0;many or extended;;6;high;;7;moderate;;8;low@0.7", "high:0;many or extended;;6;high;;7;low;;8;low@0.8", "high:0;many or extended;;6;moderate;;7;high;;8;moderate@0.25", "high:0;many or extended;;6;moderate;;7;moderate;;8;moderate@0.4", "high:0;many or extended;;6;moderate;;7;low;;8;moderate@0.65", "high:0;many or extended;;6;moderate;;7;high;;8;low@0.6", "high:0;many or extended;;6;moderate;;7;moderate;;8;low@0.5", "high:0;many or extended;;6;moderate;;7;low;;8;low@0.75", "high:0;few or short;;6;high;;7;high;;8;moderate@0.25", "high:0;few or short;;6;high;;7;moderate;;8;moderate@0.35", "high:0;few or short;;6;high;;7;low;;8;moderate@0.35", "high:0;few or short;;6;high;;7;high;;8;low@0.15", "high:0;few or short;;6;high;;7;moderate;;8;low@0.15", "high:0;few or short;;6;high;;7;low;;8;low@0.15", "high:0;few or short;;6;moderate;;7;high;;8;moderate@0.16", "high:0;few or short;;6;moderate;;7;moderate;;8;moderate@0.03", "high:0;few or short;;6;moderate;;7;low;;8;moderate@0.03", "high:0;few or short;;6;moderate;;7;high;;8;low@0.03", "high:0;few or short;;6;moderate;;7;moderate;;8;low@0.03", "high:0;few or short;;6;moderate;;7;low;;8;low@0.03", "moderate:0;many or extended;;6;high;;7;high;;8;moderate@0.4", "moderate:0;many or extended;;6;high;;7;moderate;;8;moderate@0.3", "moderate:0;many or extended;;6;high;;7;low;;8;moderate@0.2", "moderate:0;many or extended;;6;high;;7;high;;8;low@0.2", "moderate:0;many or extended;;6;high;;7;moderate;;8;low@0.15", "moderate:0;many or extended;;6;high;;7;low;;8;low@0.15", "moderate:0;many or extended;;6;moderate;;7;high;;8;moderate@0.45", "moderate:0;many or extended;;6;moderate;;7;moderate;;8;moderate@0.43", "moderate:0;many or extended;;6;moderate;;7;low;;8;moderate@0.3", "moderate:0;many or extended;;6;moderate;;7;high;;8;low@0.28", "moderate:0;many or extended;;6;moderate;;7;moderate;;8;low@0.3", "moderate:0;many or extended;;6;moderate;;7;low;;8;low@0.15", "moderate:0;few or short;;6;high;;7;high;;8;moderate@0.4", "moderate:0;few or short;;6;high;;7;moderate;;8;moderate@0.4", "moderate:0;few or short;;6;high;;7;low;;8;moderate@0.4", "moderate:0;few or short;;6;high;;7;high;;8;low@0.45", "moderate:0;few or short;;6;high;;7;moderate;;8;low@0.45", "moderate:0;few or short;;6;high;;7;low;;8;low@0.45", "moderate:0;few or short;;6;moderate;;7;high;;8;moderate@0.24", "moderate:0;few or short;;6;moderate;;7;moderate;;8;moderate@0.27", "moderate:0;few or short;;6;moderate;;7;low;;8;moderate@0.27", "moderate:0;few or short;;6;moderate;;7;high;;8;low@0.37", "moderate:0;few or short;;6;moderate;;7;moderate;;8;low@0.37", "moderate:0;few or short;;6;moderate;;7;low;;8;low@0.37", "low:0;many or extended;;6;high;;7;high;;8;moderate@0.3", "low:0;many or extended;;6;high;;7;moderate;;8;moderate@0.2", "low:0;many or extended;;6;high;;7;low;;8;moderate@0.1", "low:0;many or extended;;6;high;;7;high;;8;low@0.15", "low:0;many or extended;;6;high;;7;moderate;;8;low@0.15", "low:0;many or extended;;6;high;;7;low;;8;low@0.05", "low:0;many or extended;;6;moderate;;7;high;;8;moderate@0.3", "low:0;many or extended;;6;moderate;;7;moderate;;8;moderate@0.17", "low:0;many or extended;;6;moderate;;7;low;;8;moderate@0.05", "low:0;many or extended;;6;moderate;;7;high;;8;low@0.12", "low:0;many or extended;;6;moderate;;7;moderate;;8;low@0.2", "low:0;many or extended;;6;moderate;;7;low;;8;low@0.1", "low:0;few or short;;6;high;;7;high;;8;moderate@0.35", "low:0;few or short;;6;high;;7;moderate;;8;moderate@0.25", "low:0;few or short;;6;high;;7;low;;8;moderate@0.25", "low:0;few or short;;6;high;;7;high;;8;low@0.4", "low:0;few or short;;6;high;;7;moderate;;8;low@0.4", "low:0;few or short;;6;high;;7;low;;8;low@0.4", "low:0;few or short;;6;moderate;;7;high;;8;moderate@0.6", "low:0;few or short;;6;moderate;;7;moderate;;8;moderate@0.7", "low:0;few or short;;6;moderate;;7;low;;8;moderate@0.7", "low:0;few or short;;6;moderate;;7;high;;8;low@0.6", "low:0;few or short;;6;moderate;;7;moderate;;8;low@0.6", "low:0;few or short;;6;moderate;;7;low;;8;low@0.6"]}, {"id": 4, "edges_out": [5, 7], "edges_in": [], "unit_long": null, "unit_short": null, "values": ["good", "poor"], "probs": ["good:@0.8", "poor:@0.2"]}, {"id": 10, "edges_out": [8], "edges_in": [], "unit_long": null, "unit_short": null, "values": ["good", "poor"], "probs": ["good:@0.3", "poor:@0.7"]}]}